nonebot/adapters/mirai2/__init__.py
nonebot/adapters/mirai2/adapter.py
nonebot/adapters/mirai2/bot.py
nonebot/adapters/mirai2/bot.pyi
nonebot/adapters/mirai2/config.py
nonebot/adapters/mirai2/event/__init__.py
nonebot/adapters/mirai2/event/base.py
nonebot/adapters/mirai2/event/message.py
nonebot/adapters/mirai2/event/meta.py
nonebot/adapters/mirai2/event/notice.py
nonebot/adapters/mirai2/event/request.py
nonebot/adapters/mirai2/exception.py
nonebot/adapters/mirai2/log.py
nonebot/adapters/mirai2/message.py
nonebot/adapters/mirai2/permission.py
nonebot/adapters/mirai2/utils.py
nonebot_adapter_mirai2-0.0.22.dist-info/LICENSE
nonebot_adapter_mirai2-0.0.22.dist-info/METADATA
nonebot_adapter_mirai2-0.0.22.dist-info/WHEEL
nonebot_adapter_mirai2-0.0.22.dist-info/RECORD
