Metadata-Version: 2.1
Name: nonebot-adapter-mirai2
Version: 0.0.22
Summary: 兼容 MiraiApiHttp2.x 的 nonebot2_adapter
License: AGPL-3.0
Author: ieew
Author-email: i@ieew.cc
Requires-Python: >=3.8,<4.0.0
Classifier: License :: OSI Approved :: GNU Affero General Public License v3
Classifier: Programming Language :: Python :: 3
Classifier: Programming Language :: Python :: 3.8
Classifier: Programming Language :: Python :: 3.9
Classifier: Programming Language :: Python :: 3.10
Classifier: Programming Language :: Python :: 3.11
Requires-Dist: nonebot2 (>=2.0.0-beta.4,<3.0.0)
